simplereq.py
simplereq-0.5.0.dist-info/METADATA
simplereq-0.5.0.dist-info/WHEEL
simplereq-0.5.0.dist-info/top_level.txt
simplereq-0.5.0.dist-info/RECORD
