Metadata-Version: 2.1
Name: simplereq
Version: 0.5.0
Summary: A simple python library that is similar to requests.
Home-page: 
Author: Jiro
Author-email: contact@jiroawesome.tech
License: MIT
